xbox_smartglass_core_asyncio-0.8.10-py3.8-nspkg.pth
xbox/auxiliary/__init__.py
xbox/auxiliary/crypto.py
xbox/auxiliary/manager.py
xbox/auxiliary/packer.py
xbox/auxiliary/packet.py
xbox/auxiliary/relay.py
xbox/handlers/__init__.py
xbox/handlers/fallout4_relay.py
xbox/handlers/gamepad_input.py
xbox/handlers/text_input.py
xbox/handlers/tui.py
xbox/rest/__init__.py
xbox/rest/app.py
xbox/rest/consolewrap.py
xbox/rest/decorators.py
xbox/rest/routes/__init__.py
xbox/rest/routes/auth.py
xbox/rest/routes/device.py
xbox/rest/routes/index.py
xbox/rest/routes/versions.py
xbox/rest/routes/web.py
xbox/rest/static/style.css
xbox/rest/templates/auth_result.html
xbox/rest/templates/login.html
xbox/rest/templates/login_oauth.html
xbox/rest/templates/logout.html
xbox/scripts/__init__.py
xbox/scripts/main_cli.py
xbox/scripts/pcap.py
xbox/scripts/recrypt.py
xbox/sg/__init__.py
xbox/sg/console.py
xbox/sg/constants.py
xbox/sg/crypto.py
xbox/sg/enum.py
xbox/sg/factory.py
xbox/sg/manager.py
xbox/sg/packer.py
xbox/sg/protocol.py
xbox/sg/packet/__init__.py
xbox/sg/packet/message.py
xbox/sg/packet/simple.py
xbox/sg/utils/__init__.py
xbox/sg/utils/adapters.py
xbox/sg/utils/events.py
xbox/sg/utils/struct.py
xbox/stump/__init__.py
xbox/stump/enum.py
xbox/stump/json_model.py
xbox/stump/manager.py
xbox_smartglass_core_asyncio-0.8.10.dist-info/LICENSE
xbox_smartglass_core_asyncio-0.8.10.dist-info/METADATA
xbox_smartglass_core_asyncio-0.8.10.dist-info/WHEEL
xbox_smartglass_core_asyncio-0.8.10.dist-info/entry_points.txt
xbox_smartglass_core_asyncio-0.8.10.dist-info/namespace_packages.txt
xbox_smartglass_core_asyncio-0.8.10.dist-info/top_level.txt
xbox_smartglass_core_asyncio-0.8.10.dist-info/RECORD
