Metadata-Version: 2.1
Name: xbox-smartglass-core-asyncio
Version: 0.8.10
Summary: A library to interact with the Xbox One gaming console via the SmartGlass protocol.
Home-page: https://github.com/OpenXbox/xbox-smartglass-core-python
Author: OpenXbox
Author-email: noreply@openxbox.org
License: GPL
Keywords: xbox one smartglass auxiliary fallout title stump tv streaming livetv rest api
Platform: UNKNOWN
Classifier: Development Status :: 4 - Beta
Classifier: Intended Audience :: Developers
Classifier: License :: OSI Approved :: MIT License
Classifier: Topic :: Software Development :: Libraries :: Python Modules
Classifier: Programming Language :: Python :: 3
Classifier: Programming Language :: Python :: 3.6
Classifier: Programming Language :: Python :: 3.7
Classifier: Programming Language :: Python :: 3.8
Requires-Python: >=3.6
Requires-Dist: xbox-webapi (>=1.1.8)
Requires-Dist: construct (==2.10.56)
Requires-Dist: cryptography (==2.8)
Requires-Dist: dpkt
Requires-Dist: quart
Requires-Dist: aioconsole
Requires-Dist: marshmallow-objects
Provides-Extra: dev
Requires-Dist: bump2version ; extra == 'dev'
Requires-Dist: watchdog ; extra == 'dev'
Requires-Dist: Sphinx ; extra == 'dev'
Requires-Dist: wheel ; extra == 'dev'
Requires-Dist: twine ; extra == 'dev'
Requires-Dist: coverage ; extra == 'dev'
Requires-Dist: pytest ; extra == 'dev'
Requires-Dist: pytest-runner ; extra == 'dev'
Requires-Dist: pytest-console-scripts ; extra == 'dev'
Requires-Dist: pytest-asyncio ; extra == 'dev'
